LICENSE
MANIFEST.in
README.rst
jw2html.ini
setup.py
JW2HTML.egg-info/PKG-INFO
JW2HTML.egg-info/SOURCES.txt
JW2HTML.egg-info/dependency_links.txt
JW2HTML.egg-info/entry_points.txt
JW2HTML.egg-info/requires.txt
JW2HTML.egg-info/top_level.txt
jw2html/__init__.py
jw2html/config.py
jw2html/jw2html.py