Metadata-Version: 1.0
Name: JW2HTML
Version: 0.1
Summary: JW2HTML converts an issue of the Jungle World from the website to a single HTML file to be used for epub conversion by e.g. calibre.
Home-page: https://github.com/marmorkuchen/jw2html
Author: marmorkuchen
Author-email: marmorkuchen@kodeaffe.de
License: GPL
Keywords: jungle world newspaper html epub convert
Platform: UNKNOWN
